{"type":"PR","pr":{"number":2,"head":"020c5ccf2cb1dd3cec90bfdb478b9de4df9cc54b"},"user":"Greg Hawthorne","status":"pending_publish","branch":"cms/pages/home","collection":"pages","commitMessage":"Update Pages “home”","title":"Digital Marketing for Your Business","description":"Neque porro quisquam est qui dolorem ipsum quia dolor sit amet, consectetur, adipisci velit...","objects":{"entry":{"path":"src/pages/index.md","sha":"0f36d702b26f2a884fbe9c6145ad64ecabbe0bb2"},"files":[]},"timeStamp":"2020-01-15T12:07:58.784Z","version":"1"}